hpke_http/__init__.py
hpke_http/_logging.py
hpke_http/constants.py
hpke_http/core.py
hpke_http/exceptions.py
hpke_http/headers.py
hpke_http/hpke.py
hpke_http/py.typed
hpke_http/streaming.py
hpke_http/middleware/__init__.py
hpke_http/middleware/aiohttp.py
hpke_http/middleware/fastapi.py
hpke_http/middleware/httpx.py
hpke_http/primitives/__init__.py
hpke_http/primitives/aead.py
hpke_http/primitives/kdf.py
hpke_http/primitives/kem.py
hpke_http-1.2.0.dist-info/METADATA
hpke_http-1.2.0.dist-info/WHEEL
hpke_http-1.2.0.dist-info/top_level.txt
hpke_http-1.2.0.dist-info/RECORD
