Metadata-Version: 2.4
Name: hpke_http
Version: 1.2.0
Summary: End-to-end encryption for HTTP APIs using RFC 9180 HPKE. Drop-in middleware for FastAPI, aiohttp, and httpx.
Author: Duale AI
License-Expression: Apache-2.0
Project-URL: Homepage, https://github.com/dualeai/hpke-http
Project-URL: Documentation, https://github.com/dualeai/hpke-http#readme
Project-URL: Repository, https://github.com/dualeai/hpke-http.git
Project-URL: Changelog, https://github.com/dualeai/hpke-http/releases
Project-URL: Issues, https://github.com/dualeai/hpke-http/issues
Keywords: hpke,encryption,rfc9180,cryptography,http,e2e,chacha20,x25519,fastapi,aiohttp,httpx,sse,streaming
Classifier: Development Status :: 4 - Beta
Classifier: Intended Audience :: Developers
Classifier: Operating System :: OS Independent
Classifier: Programming Language :: Python :: 3
Classifier: Programming Language :: Python :: 3.10
Classifier: Programming Language :: Python :: 3.11
Classifier: Programming Language :: Python :: 3.12
Classifier: Programming Language :: Python :: 3.13
Classifier: Programming Language :: Python :: 3.14
Classifier: Programming Language :: Python :: Implementation :: CPython
Classifier: Topic :: Security :: Cryptography
Classifier: Topic :: Internet :: WWW/HTTP
Classifier: Typing :: Typed
Requires-Python: >=3.10
Requires-Dist: cryptography~=46.0
Provides-Extra: dev
Requires-Dist: granian~=2.0; extra == "dev"
Requires-Dist: hypothesis~=6.148; extra == "dev"
Requires-Dist: py-spy~=0.4; extra == "dev"
Requires-Dist: pyright~=1.1; extra == "dev"
Requires-Dist: pytest-asyncio~=0.24; extra == "dev"
Requires-Dist: pytest-cov~=7.0; extra == "dev"
Requires-Dist: pytest-mock~=3.14; extra == "dev"
Requires-Dist: pytest-xdist[psutil]~=3.8; extra == "dev"
Requires-Dist: pytest~=8.3; extra == "dev"
Requires-Dist: python-multipart~=0.0; extra == "dev"
Requires-Dist: ruff~=0.7; extra == "dev"
Requires-Dist: scipy~=1.14; extra == "dev"
Requires-Dist: twine~=6.1; extra == "dev"
Requires-Dist: typing_extensions~=4.12; extra == "dev"
Requires-Dist: vulture~=2.14; extra == "dev"
Provides-Extra: testing
Requires-Dist: pytest-asyncio~=0.24; extra == "testing"
Requires-Dist: pytest~=8.3; extra == "testing"
Provides-Extra: fastapi
Requires-Dist: starlette~=0.50; extra == "fastapi"
Provides-Extra: aiohttp
Requires-Dist: aiohttp~=3.13; extra == "aiohttp"
Provides-Extra: httpx
Requires-Dist: httpx~=0.28; extra == "httpx"
Provides-Extra: zstd
Requires-Dist: backports.zstd>=1.0; python_version < "3.14" and extra == "zstd"
